py_thorlabs_tsp/__init__.py
py_thorlabs_tsp/constants.py
py_thorlabs_tsp/dll_routines.py
py_thorlabs_tsp/errors.py
py_thorlabs_tsp/thorlabs_tsp01b.py
py_thorlabs_tsp/typedef.py
py_thorlabs_tsp/wrappers.py
py_thorlabs_tsp-0.0.8.dist-info/LICENSE
py_thorlabs_tsp-0.0.8.dist-info/LICENSE_THORLABS
py_thorlabs_tsp-0.0.8.dist-info/METADATA
py_thorlabs_tsp-0.0.8.dist-info/WHEEL
py_thorlabs_tsp-0.0.8.dist-info/top_level.txt
py_thorlabs_tsp-0.0.8.dist-info/RECORD
