Metadata-Version: 2.1
Name: py-thorlabs-tsp
Version: 0.0.8
Summary: Controls for Thorlabs TSP01 temperature and humidity sensor
Home-page: https://gitlab.com/dimapu/py_thorlabs_tsp
Author: Dzmitry Pustakhod, TU/e - PITC
Author-email: d.pustakhod@tue.nl
License: MIT License
Platform: UNKNOWN
Classifier: Development Status :: 4 - Beta
Classifier: License :: OSI Approved :: MIT License
Classifier: Operating System :: Microsoft :: Windows
Classifier: Operating System :: Microsoft :: Windows :: Windows 7
Classifier: Operating System :: Microsoft :: Windows :: Windows 10
Classifier: Programming Language :: Python
Classifier: Programming Language :: Python :: 3
Classifier: Programming Language :: Python :: 3.7
Classifier: Programming Language :: Python :: 3 :: Only
Classifier: Topic :: Scientific/Engineering
Classifier: Topic :: System :: Hardware
Classifier: Topic :: System :: Hardware :: Hardware Drivers
